orca/__init__.py
orca/__main__.py
orca/cli/__init__.py
orca/cli/commands.py
orca/core/__init__.py
orca/core/config.py
orca/core/errors.py
orca/core/handler.py
orca/core/ledger.py
orca/core/tasks.py
orca/schema/ORCA_SCHEMA_1.0.json
orca/schema/__init__.py
orca/schema/validation.py
tests/fixtures/__init__.py
tests/fixtures/inputs.py
tests/fixtures/no_inputs.py
tests/integration/__init__.py
tests/integration/command_test.py
tests/integration/dotfile_handler_test.py
tests/integration/exec_handler_test.py
tests/integration/ledger_test.py
tests/integration/schema_test.py
tests/mocks/__init__.py
tests/mocks/conditions.py
tests/mocks/tasks.py
tests/unit/__init__.py
tests/unit/handler_test.py
amanzi.orca-0.5.3.dist-info/LICENSE
amanzi.orca-0.5.3.dist-info/METADATA
amanzi.orca-0.5.3.dist-info/WHEEL
amanzi.orca-0.5.3.dist-info/entry_points.txt
amanzi.orca-0.5.3.dist-info/top_level.txt
amanzi.orca-0.5.3.dist-info/RECORD
