Metadata-Version: 2.1
Name: amanzi.orca
Version: 0.5.3
Summary: A cli tool for orchestrating model workflows
Home-page: https://github.com/KoduIsGreat/orca.git
Author: Adam Shelton, Olaf David
Author-email: adamshelton@rti.org
License: UNKNOWN
Platform: UNKNOWN
Classifier: Development Status :: 3 - Alpha
Classifier: License :: OSI Approved :: GNU General Public License v3 (GPLv3)
Classifier: Intended Audience :: Developers
Requires-Dist: csip (==0.8.13)
Requires-Dist: jsonschema (==3.0.1)
Requires-Dist: click (==7.0)
Requires-Dist: click-log (==0.3.2)
Requires-Dist: dotted (==0.1.8)
Requires-Dist: ruamel.yaml (==0.15.88)
Requires-Dist: pymongo (==3.7.2)
Requires-Dist: requests (==2.21.0)
Requires-Dist: pykafka (==2.8.0)
